untropy/__init__.py
untropy/__main__.py
untropy/cli/__init__.py
untropy/cli/alias.py
untropy/cli/cli.py
untropy/cli/cookie.py
untropy/cli/env.py
untropy/config/__init__.py
untropy/config/load.py
untropy/config/model.py
untropy/utils/__init__.py
untropy/utils/jinja.py
untropy/utils/log.py
untropy/utils/log_setup.py
untropy/utils/random_name.py
untropy-0.1.0.data/data/share/untropy/cookies/.gitkeep
untropy-0.1.0.dist-info/entry_points.txt
untropy-0.1.0.dist-info/LICENSE
untropy-0.1.0.dist-info/WHEEL
untropy-0.1.0.dist-info/METADATA
untropy-0.1.0.dist-info/RECORD
