Metadata-Version: 2.1
Name: untropy
Version: 0.1.0
Summary: Flexible command line tool to manage fullstack development projects.
Keywords: untropy,devops
Author-email: Antoine Martin <antoine@mrtn.fr>
Requires-Python: >=3.8
Classifier: Development Status :: 2 - Pre-Alpha
Classifier: Environment :: Console
Classifier: Intended Audience :: Developers
Classifier: Intended Audience :: System Administrators
Classifier: License :: OSI Approved :: Apache Software License
Classifier: Natural Language :: English
Classifier: Operating System :: OS Independent
Classifier: Programming Language :: Python
Classifier: Programming Language :: Python :: 3
Classifier: Programming Language :: Python :: 3 :: Only
Classifier: Programming Language :: Python :: 3.8
Classifier: Programming Language :: Python :: 3.9
Classifier: Programming Language :: Python :: 3.10
Classifier: Topic :: Security
Classifier: Topic :: Software Development
Classifier: Topic :: Software Development :: Build Tools
Classifier: Topic :: Software Development :: Version Control
Classifier: Typing :: Typed
Classifier: Topic :: Utilities
Requires-Dist: click==8.0.4
Requires-Dist: python-dotenv==0.19.2
Requires-Dist: toml>=0.10.1,<0.11
Requires-Dist: pydantic==1.9.0
Requires-Dist: coloredlogs==15.0.1
Requires-Dist: timeago==1.0.14
Requires-Dist: selinux==0.2.1
Requires-Dist: twine==3.8.0
Requires-Dist: cookiecutter==1.7.3
Requires-Dist: mdformat==0.7.13
Requires-Dist: mdformat-tables==0.4.1
Requires-Dist: cryptography>=3.4.8
Requires-Dist: PyYAML==6.0
Requires-Dist: asynctest ; extra == "test"
Requires-Dist: pytest ; extra == "test"
Requires-Dist: pytest-cache ; extra == "test"
Requires-Dist: pytest-cov ; extra == "test"
Requires-Dist: pytest-asyncio ; extra == "test"
Requires-Dist: pytest-mock ; extra == "test"
Requires-Dist: coverage ; extra == "test"
Requires-Dist: flake8 ; extra == "test"
Requires-Dist: mypy ; extra == "test"
Requires-Dist: mypy-extensions ; extra == "test"
Requires-Dist: requests ; extra == "test"
Requires-Dist: isort ; extra == "test"
Requires-Dist: black ; extra == "test"
Requires-Dist: poethepoet ; extra == "test"
Requires-Dist: types-toml ; extra == "test"
Requires-Dist: types-pytz ; extra == "test"
Requires-Dist: types-requests ; extra == "test"
Requires-Dist: types-setuptools ; extra == "test"
Requires-Dist: types-PyYAML ; extra == "test"
Project-URL: Home, https://github.com/untropy/untropy
Provides-Extra: test
